winapy_gdi.cp39-win_amd64.pyd
winapy_mme.cp39-win_amd64.pyd
winapy_shell.cp39-win_amd64.pyd
winapy_user.cp39-win_amd64.pyd
winapy/__init__.py
winapy-0.1.2.data/data/utils.c
winapy-0.1.2.data/data/utils.h
winapy_con/__init__.py
winapy-0.1.2.dist-info/METADATA
winapy-0.1.2.dist-info/WHEEL
winapy-0.1.2.dist-info/top_level.txt
winapy-0.1.2.dist-info/RECORD
