Metadata-Version: 2.1
Name: winapy
Version: 0.1.2
Summary: A WinAPI (Windows API) wrapper made in C for Python.
Home-page: https://github.com/Itzsten/WinAPY
Author: Itzsten
Author-email: itzsten@gmail.com
Classifier: Programming Language :: Python :: 3
Classifier: License :: OSI Approved :: MIT License
Classifier: Operating System :: Microsoft :: Windows
Classifier: Intended Audience :: Education
Classifier: Development Status :: 4 - Beta
Requires-Python: >=3
